correction_helper.py
correction_helper-2025.12.5.dist-info/METADATA
correction_helper-2025.12.5.dist-info/WHEEL
correction_helper-2025.12.5.dist-info/top_level.txt
correction_helper-2025.12.5.dist-info/RECORD
