Metadata-Version: 2.4
Name: correction-helper
Version: 2025.12.5
Summary: Some helpers to help writing correction bots, use by hackinscience.org.
Author-email: Julien Palard <julien@palard.fr>
License-Expression: MIT
Project-URL: Homepage, https://github.com/JulienPalard/correction-helper
Classifier: Development Status :: 5 - Production/Stable
Classifier: Intended Audience :: Developers
Classifier: Natural Language :: English
Classifier: Programming Language :: Python :: 3
Requires-Python: >=3.7
Requires-Dist: friendly-traceback>=0.4.87
Requires-Dist: forking>=0.2
